dobwidget/__init__.py
django_dob_widget-1.2.0.dist-info/LICENSE
django_dob_widget-1.2.0.dist-info/METADATA
django_dob_widget-1.2.0.dist-info/WHEEL
django_dob_widget-1.2.0.dist-info/top_level.txt
django_dob_widget-1.2.0.dist-info/RECORD
