Metadata-Version: 2.1
Name: django-dob-widget
Version: 1.2.0
Summary: A Django date widget optimised for usability in entering dates of birth
Home-page: https://github.com/matthewwilkes/django-dob-widget
Author: Matthew Wilkes
Author-email: django-dobwidget@matthewwilkes.name
License: MIT
Keywords: django,widget,date
Platform: linux
Classifier: Development Status :: 5 - Production/Stable
Classifier: Environment :: Web Environment
Classifier: Framework :: Django
Classifier: Intended Audience :: Developers
Classifier: License :: OSI Approved :: BSD License
Classifier: Operating System :: Unix
Classifier: Programming Language :: Python
Classifier: Programming Language :: Python :: 2
Classifier: Programming Language :: Python :: 2.7
Classifier: Programming Language :: Python :: 3
Classifier: Programming Language :: Python :: 3.5
Classifier: Framework :: Django
Classifier: Framework :: Django :: 1.10
Classifier: Topic :: Software Development :: Widget Sets
